[
  { "inputs": [], "stateMutability": "nonpayable", "type": "constructor" },
  { "inputs": [], "name": "AlreadyInstalled", "type": "error" },
  { "inputs": [], "name": "InvalidEtherFiNodeVersion", "type": "error" },
  { "inputs": [], "name": "InvalidParams", "type": "error" },
  { "inputs": [], "name": "InvalidPenaltyRate", "type": "error" },
  { "inputs": [], "name": "NonZeroAddress", "type": "error" },
  { "inputs": [], "name": "NotAdmin", "type": "error" },
  { "inputs": [], "name": "NotInstalled", "type": "error" },
  { "inputs": [], "name": "NotStakingManager", "type": "error" },
  { "inputs": [], "name": "SendFail", "type": "error" },
  {
    "anonymous": false,
    "inputs": [
      {
        "indexed": false,
        "internalType": "address",
        "name": "previousAdmin",
        "type": "address"
      },
      {
        "indexed": false,
        "internalType": "address",
        "name": "newAdmin",
        "type": "address"
      }
    ],
    "name": "AdminChanged",
    "type": "event"
  },
  {
    "anonymous": false,
    "inputs": [
      {
        "indexed": true,
        "internalType": "address",
        "name": "beacon",
        "type": "address"
      }
    ],
    "name": "BeaconUpgraded",
    "type": "event"
  },
  {
    "anonymous": false,
    "inputs": [
      {
        "indexed": true,
        "internalType": "uint256",
        "name": "_validatorId",
        "type": "uint256"
      },
      {
        "indexed": true,
        "internalType": "address",
        "name": "etherFiNode",
        "type": "address"
      },
      {
        "indexed": false,
        "internalType": "uint256",
        "name": "toOperator",
        "type": "uint256"
      },
      {
        "indexed": false,
        "internalType": "uint256",
        "name": "toTnft",
        "type": "uint256"
      },
      {
        "indexed": false,
        "internalType": "uint256",
        "name": "toBnft",
        "type": "uint256"
      },
      {
        "indexed": false,
        "internalType": "uint256",
        "name": "toTreasury",
        "type": "uint256"
      }
    ],
    "name": "FullWithdrawal",
    "type": "event"
  },
  {
    "anonymous": false,
    "inputs": [
      {
        "indexed": true,
        "internalType": "uint256",
        "name": "_validatorId",
        "type": "uint256"
      },
      {
        "indexed": false,
        "internalType": "uint256",
        "name": "amount",
        "type": "uint256"
      }
    ],
    "name": "FundsWithdrawn",
    "type": "event"
  },
  {
    "anonymous": false,
    "inputs": [
      {
        "indexed": false,
        "internalType": "uint8",
        "name": "version",
        "type": "uint8"
      }
    ],
    "name": "Initialized",
    "type": "event"
  },
  {
    "anonymous": false,
    "inputs": [
      {
        "indexed": false,
        "internalType": "uint256",
        "name": "_validatorId",
        "type": "uint256"
      }
    ],
    "name": "NodeEvicted",
    "type": "event"
  },
  {
    "anonymous": false,
    "inputs": [
      {
        "indexed": false,
        "internalType": "uint256",
        "name": "_validatorId",
        "type": "uint256"
      }
    ],
    "name": "NodeExitProcessed",
    "type": "event"
  },
  {
    "anonymous": false,
    "inputs": [
      {
        "indexed": false,
        "internalType": "uint256",
        "name": "_validatorId",
        "type": "uint256"
      }
    ],
    "name": "NodeExitRequestReverted",
    "type": "event"
  },
  {
    "anonymous": false,
    "inputs": [
      {
        "indexed": false,
        "internalType": "uint256",
        "name": "_validatorId",
        "type": "uint256"
      }
    ],
    "name": "NodeExitRequested",
    "type": "event"
  },
  {
    "anonymous": false,
    "inputs": [
      {
        "indexed": true,
        "internalType": "address",
        "name": "previousOwner",
        "type": "address"
      },
      {
        "indexed": true,
        "internalType": "address",
        "name": "newOwner",
        "type": "address"
      }
    ],
    "name": "OwnershipTransferred",
    "type": "event"
  },
  {
    "anonymous": false,
    "inputs": [
      {
        "indexed": true,
        "internalType": "uint256",
        "name": "_validatorId",
        "type": "uint256"
      },
      {
        "indexed": true,
        "internalType": "address",
        "name": "etherFiNode",
        "type": "address"
      },
      {
        "indexed": false,
        "internalType": "uint256",
        "name": "toOperator",
        "type": "uint256"
      },
      {
        "indexed": false,
        "internalType": "uint256",
        "name": "toTnft",
        "type": "uint256"
      },
      {
        "indexed": false,
        "internalType": "uint256",
        "name": "toBnft",
        "type": "uint256"
      },
      {
        "indexed": false,
        "internalType": "uint256",
        "name": "toTreasury",
        "type": "uint256"
      }
    ],
    "name": "PartialWithdrawal",
    "type": "event"
  },
  {
    "anonymous": false,
    "inputs": [
      {
        "indexed": false,
        "internalType": "address",
        "name": "account",
        "type": "address"
      }
    ],
    "name": "Paused",
    "type": "event"
  },
  {
    "anonymous": false,
    "inputs": [
      {
        "indexed": true,
        "internalType": "uint256",
        "name": "_validatorId",
        "type": "uint256"
      },
      {
        "indexed": false,
        "internalType": "enum IEtherFiNode.VALIDATOR_PHASE",
        "name": "_phase",
        "type": "uint8"
      }
    ],
    "name": "PhaseChanged",
    "type": "event"
  },
  {
    "anonymous": false,
    "inputs": [
      {
        "indexed": false,
        "internalType": "address",
        "name": "account",
        "type": "address"
      }
    ],
    "name": "Unpaused",
    "type": "event"
  },
  {
    "anonymous": false,
    "inputs": [
      {
        "indexed": true,
        "internalType": "address",
        "name": "implementation",
        "type": "address"
      }
    ],
    "name": "Upgraded",
    "type": "event"
  },
  {
    "inputs": [],
    "name": "DEPRECATED_admin",
    "outputs": [{ "internalType": "address", "name": "", "type": "address" }],
    "stateMutability": "view",
    "type": "function"
  },
  {
    "inputs": [],
    "name": "DEPRECATED_protocolRevenueManager",
    "outputs": [
      {
        "internalType": "contract IProtocolRevenueManager",
        "name": "",
        "type": "address"
      }
    ],
    "stateMutability": "view",
    "type": "function"
  },
  {
    "inputs": [],
    "name": "DEPRECATED_protocolRevenueManagerContract",
    "outputs": [{ "internalType": "address", "name": "", "type": "address" }],
    "stateMutability": "view",
    "type": "function"
  },
  {
    "inputs": [],
    "name": "DEPRECATED_protocolRewardsSplit",
    "outputs": [
      { "internalType": "uint64", "name": "treasury", "type": "uint64" },
      { "internalType": "uint64", "name": "nodeOperator", "type": "uint64" },
      { "internalType": "uint64", "name": "tnft", "type": "uint64" },
      { "internalType": "uint64", "name": "bnft", "type": "uint64" }
    ],
    "stateMutability": "view",
    "type": "function"
  },
  {
    "inputs": [],
    "name": "SCALE",
    "outputs": [{ "internalType": "uint64", "name": "", "type": "uint64" }],
    "stateMutability": "view",
    "type": "function"
  },
  {
    "inputs": [{ "internalType": "address", "name": "", "type": "address" }],
    "name": "admins",
    "outputs": [{ "internalType": "bool", "name": "", "type": "bool" }],
    "stateMutability": "view",
    "type": "function"
  },
  {
    "inputs": [
      { "internalType": "bool", "name": "_enableRestaking", "type": "bool" }
    ],
    "name": "allocateEtherFiNode",
    "outputs": [
      {
        "internalType": "address",
        "name": "withdrawalSafeAddress",
        "type": "address"
      }
    ],
    "stateMutability": "nonpayable",
    "type": "function"
  },
  {
    "inputs": [],
    "name": "auctionManager",
    "outputs": [
      {
        "internalType": "contract IAuctionManager",
        "name": "",
        "type": "address"
      }
    ],
    "stateMutability": "view",
    "type": "function"
  },
  {
    "inputs": [
      {
        "internalType": "uint256[]",
        "name": "_validatorIds",
        "type": "uint256[]"
      }
    ],
    "name": "batchFullWithdraw",
    "outputs": [],
    "stateMutability": "nonpayable",
    "type": "function"
  },
  {
    "inputs": [
      {
        "internalType": "uint256[]",
        "name": "_validatorIds",
        "type": "uint256[]"
      }
    ],
    "name": "batchPartialWithdraw",
    "outputs": [],
    "stateMutability": "nonpayable",
    "type": "function"
  },
  {
    "inputs": [
      {
        "internalType": "uint256[]",
        "name": "_validatorIds",
        "type": "uint256[]"
      }
    ],
    "name": "batchQueueRestakedWithdrawal",
    "outputs": [],
    "stateMutability": "nonpayable",
    "type": "function"
  },
  {
    "inputs": [
      {
        "internalType": "uint256[]",
        "name": "_validatorIds",
        "type": "uint256[]"
      }
    ],
    "name": "batchRevertExitRequest",
    "outputs": [],
    "stateMutability": "nonpayable",
    "type": "function"
  },
  {
    "inputs": [
      {
        "internalType": "uint256[]",
        "name": "_validatorIds",
        "type": "uint256[]"
      }
    ],
    "name": "batchSendExitRequest",
    "outputs": [],
    "stateMutability": "nonpayable",
    "type": "function"
  },
  {
    "inputs": [],
    "name": "bnft",
    "outputs": [
      { "internalType": "contract BNFT", "name": "", "type": "address" }
    ],
    "stateMutability": "view",
    "type": "function"
  },
  {
    "inputs": [
      { "internalType": "uint256", "name": "_validatorId", "type": "uint256" },
      { "internalType": "uint256", "name": "_beaconBalance", "type": "uint256" }
    ],
    "name": "calculateTVL",
    "outputs": [
      {
        "internalType": "uint256",
        "name": "toNodeOperator",
        "type": "uint256"
      },
      { "internalType": "uint256", "name": "toTnft", "type": "uint256" },
      { "internalType": "uint256", "name": "toBnft", "type": "uint256" },
      { "internalType": "uint256", "name": "toTreasury", "type": "uint256" }
    ],
    "stateMutability": "view",
    "type": "function"
  },
  {
    "inputs": [
      {
        "internalType": "uint256[]",
        "name": "_validatorIds",
        "type": "uint256[]"
      },
      { "internalType": "bytes[]", "name": "data", "type": "bytes[]" }
    ],
    "name": "callDelayedWithdrawalRouter",
    "outputs": [
      { "internalType": "bytes[]", "name": "returnData", "type": "bytes[]" }
    ],
    "stateMutability": "nonpayable",
    "type": "function"
  },
  {
    "inputs": [
      {
        "internalType": "uint256[]",
        "name": "_validatorIds",
        "type": "uint256[]"
      },
      { "internalType": "bytes[]", "name": "data", "type": "bytes[]" }
    ],
    "name": "callDelegationManager",
    "outputs": [
      { "internalType": "bytes[]", "name": "returnData", "type": "bytes[]" }
    ],
    "stateMutability": "nonpayable",
    "type": "function"
  },
  {
    "inputs": [
      {
        "internalType": "uint256[]",
        "name": "_validatorIds",
        "type": "uint256[]"
      },
      { "internalType": "bytes[]", "name": "data", "type": "bytes[]" }
    ],
    "name": "callEigenPod",
    "outputs": [
      { "internalType": "bytes[]", "name": "returnData", "type": "bytes[]" }
    ],
    "stateMutability": "nonpayable",
    "type": "function"
  },
  {
    "inputs": [
      {
        "internalType": "uint256[]",
        "name": "_validatorIds",
        "type": "uint256[]"
      },
      { "internalType": "bytes[]", "name": "data", "type": "bytes[]" }
    ],
    "name": "callEigenPodManager",
    "outputs": [
      { "internalType": "bytes[]", "name": "returnData", "type": "bytes[]" }
    ],
    "stateMutability": "nonpayable",
    "type": "function"
  },
  {
    "inputs": [
      { "internalType": "uint256", "name": "_count", "type": "uint256" },
      { "internalType": "bool", "name": "_enableRestaking", "type": "bool" }
    ],
    "name": "createUnusedWithdrawalSafe",
    "outputs": [
      { "internalType": "address[]", "name": "", "type": "address[]" }
    ],
    "stateMutability": "nonpayable",
    "type": "function"
  },
  {
    "inputs": [],
    "name": "delayedWithdrawalRouter",
    "outputs": [
      {
        "internalType": "contract IDelayedWithdrawalRouter",
        "name": "",
        "type": "address"
      }
    ],
    "stateMutability": "view",
    "type": "function"
  },
  {
    "inputs": [],
    "name": "delegationManager",
    "outputs": [
      {
        "internalType": "contract IDelegationManager",
        "name": "",
        "type": "address"
      }
    ],
    "stateMutability": "view",
    "type": "function"
  },
  {
    "inputs": [
      { "internalType": "address", "name": "_addres", "type": "address" }
    ],
    "name": "disableEigenLayerOperatingAdmin",
    "outputs": [],
    "stateMutability": "nonpayable",
    "type": "function"
  },
  {
    "inputs": [{ "internalType": "address", "name": "", "type": "address" }],
    "name": "eigenLayerOperatingAdmin",
    "outputs": [{ "internalType": "bool", "name": "", "type": "bool" }],
    "stateMutability": "view",
    "type": "function"
  },
  {
    "inputs": [],
    "name": "eigenPodManager",
    "outputs": [
      {
        "internalType": "contract IEigenPodManager",
        "name": "",
        "type": "address"
      }
    ],
    "stateMutability": "view",
    "type": "function"
  },
  {
    "inputs": [],
    "name": "enableNodeRecycling",
    "outputs": [{ "internalType": "bool", "name": "", "type": "bool" }],
    "stateMutability": "view",
    "type": "function"
  },
  {
    "inputs": [{ "internalType": "uint256", "name": "", "type": "uint256" }],
    "name": "etherfiNodeAddress",
    "outputs": [{ "internalType": "address", "name": "", "type": "address" }],
    "stateMutability": "view",
    "type": "function"
  },
  {
    "inputs": [
      { "internalType": "uint256", "name": "_validatorId", "type": "uint256" }
    ],
    "name": "forcePartialWithdraw",
    "outputs": [],
    "stateMutability": "nonpayable",
    "type": "function"
  },
  {
    "inputs": [
      { "internalType": "uint256", "name": "_validatorId", "type": "uint256" }
    ],
    "name": "fullWithdraw",
    "outputs": [],
    "stateMutability": "nonpayable",
    "type": "function"
  },
  {
    "inputs": [
      { "internalType": "address", "name": "_address", "type": "address" }
    ],
    "name": "generateWithdrawalCredentials",
    "outputs": [{ "internalType": "bytes", "name": "", "type": "bytes" }],
    "stateMutability": "pure",
    "type": "function"
  },
  {
    "inputs": [
      { "internalType": "uint256", "name": "_validatorId", "type": "uint256" }
    ],
    "name": "getEigenPod",
    "outputs": [{ "internalType": "address", "name": "", "type": "address" }],
    "stateMutability": "view",
    "type": "function"
  },
  {
    "inputs": [
      { "internalType": "uint256", "name": "_validatorId", "type": "uint256" }
    ],
    "name": "getFullWithdrawalPayouts",
    "outputs": [
      {
        "internalType": "uint256",
        "name": "toNodeOperator",
        "type": "uint256"
      },
      { "internalType": "uint256", "name": "toTnft", "type": "uint256" },
      { "internalType": "uint256", "name": "toBnft", "type": "uint256" },
      { "internalType": "uint256", "name": "toTreasury", "type": "uint256" }
    ],
    "stateMutability": "view",
    "type": "function"
  },
  {
    "inputs": [],
    "name": "getImplementation",
    "outputs": [{ "internalType": "address", "name": "", "type": "address" }],
    "stateMutability": "view",
    "type": "function"
  },
  {
    "inputs": [
      { "internalType": "uint256", "name": "_validatorId", "type": "uint256" }
    ],
    "name": "getNonExitPenalty",
    "outputs": [
      { "internalType": "uint256", "name": "nonExitPenalty", "type": "uint256" }
    ],
    "stateMutability": "view",
    "type": "function"
  },
  {
    "inputs": [
      { "internalType": "uint256", "name": "_validatorId", "type": "uint256" }
    ],
    "name": "getRewardsPayouts",
    "outputs": [
      { "internalType": "uint256", "name": "", "type": "uint256" },
      { "internalType": "uint256", "name": "", "type": "uint256" },
      { "internalType": "uint256", "name": "", "type": "uint256" },
      { "internalType": "uint256", "name": "", "type": "uint256" }
    ],
    "stateMutability": "view",
    "type": "function"
  },
  {
    "inputs": [],
    "name": "getUnusedWithdrawalSafesLength",
    "outputs": [{ "internalType": "uint256", "name": "", "type": "uint256" }],
    "stateMutability": "view",
    "type": "function"
  },
  {
    "inputs": [
      { "internalType": "uint256", "name": "_validatorId", "type": "uint256" }
    ],
    "name": "getValidatorInfo",
    "outputs": [
      {
        "components": [
          {
            "internalType": "uint32",
            "name": "validatorIndex",
            "type": "uint32"
          },
          {
            "internalType": "uint32",
            "name": "exitRequestTimestamp",
            "type": "uint32"
          },
          {
            "internalType": "uint32",
            "name": "exitTimestamp",
            "type": "uint32"
          },
          {
            "internalType": "enum IEtherFiNode.VALIDATOR_PHASE",
            "name": "phase",
            "type": "uint8"
          }
        ],
        "internalType": "struct IEtherFiNodesManager.ValidatorInfo",
        "name": "",
        "type": "tuple"
      }
    ],
    "stateMutability": "view",
    "type": "function"
  },
  {
    "inputs": [
      { "internalType": "uint256", "name": "_validatorId", "type": "uint256" }
    ],
    "name": "getWithdrawalCredentials",
    "outputs": [{ "internalType": "bytes", "name": "", "type": "bytes" }],
    "stateMutability": "view",
    "type": "function"
  },
  {
    "inputs": [
      { "internalType": "uint256", "name": "_validatorId", "type": "uint256" }
    ],
    "name": "getWithdrawalSafeAddress",
    "outputs": [{ "internalType": "address", "name": "", "type": "address" }],
    "stateMutability": "view",
    "type": "function"
  },
  {
    "inputs": [
      { "internalType": "uint64", "name": "_count", "type": "uint64" }
    ],
    "name": "incrementNumberOfValidators",
    "outputs": [],
    "stateMutability": "nonpayable",
    "type": "function"
  },
  {
    "inputs": [
      {
        "internalType": "address",
        "name": "_treasuryContract",
        "type": "address"
      },
      {
        "internalType": "address",
        "name": "_auctionContract",
        "type": "address"
      },
      {
        "internalType": "address",
        "name": "_stakingManagerContract",
        "type": "address"
      },
      { "internalType": "address", "name": "_tnftContract", "type": "address" },
      { "internalType": "address", "name": "_bnftContract", "type": "address" }
    ],
    "name": "initialize",
    "outputs": [],
    "stateMutability": "nonpayable",
    "type": "function"
  },
  {
    "inputs": [
      { "internalType": "address", "name": "_etherFiAdmin", "type": "address" },
      {
        "internalType": "address",
        "name": "_eigenPodManager",
        "type": "address"
      },
      {
        "internalType": "address",
        "name": "_delayedWithdrawalRouter",
        "type": "address"
      },
      {
        "internalType": "uint8",
        "name": "_maxEigenlayerWithdrawals",
        "type": "uint8"
      }
    ],
    "name": "initializeOnUpgrade",
    "outputs": [],
    "stateMutability": "nonpayable",
    "type": "function"
  },
  {
    "inputs": [
      {
        "internalType": "address",
        "name": "_delegationManager",
        "type": "address"
      }
    ],
    "name": "initializeOnUpgrade2",
    "outputs": [],
    "stateMutability": "nonpayable",
    "type": "function"
  },
  {
    "inputs": [
      { "internalType": "uint256", "name": "_validatorId", "type": "uint256" }
    ],
    "name": "isExitRequested",
    "outputs": [{ "internalType": "bool", "name": "", "type": "bool" }],
    "stateMutability": "view",
    "type": "function"
  },
  {
    "inputs": [
      { "internalType": "uint256", "name": "_validatorId", "type": "uint256" }
    ],
    "name": "isRestakingEnabled",
    "outputs": [{ "internalType": "bool", "name": "", "type": "bool" }],
    "stateMutability": "view",
    "type": "function"
  },
  {
    "inputs": [
      {
        "internalType": "uint256[]",
        "name": "_validatorIds",
        "type": "uint256[]"
      }
    ],
    "name": "markBeingSlashed",
    "outputs": [],
    "stateMutability": "nonpayable",
    "type": "function"
  },
  {
    "inputs": [],
    "name": "maxEigenlayerWithdrawals",
    "outputs": [{ "internalType": "uint8", "name": "", "type": "uint8" }],
    "stateMutability": "view",
    "type": "function"
  },
  {
    "inputs": [],
    "name": "nonExitPenaltyDailyRate",
    "outputs": [{ "internalType": "uint64", "name": "", "type": "uint64" }],
    "stateMutability": "view",
    "type": "function"
  },
  {
    "inputs": [],
    "name": "nonExitPenaltyPrincipal",
    "outputs": [{ "internalType": "uint64", "name": "", "type": "uint64" }],
    "stateMutability": "view",
    "type": "function"
  },
  {
    "inputs": [
      { "internalType": "uint256", "name": "_validatorId", "type": "uint256" }
    ],
    "name": "numAssociatedValidators",
    "outputs": [{ "internalType": "uint256", "name": "", "type": "uint256" }],
    "stateMutability": "view",
    "type": "function"
  },
  {
    "inputs": [],
    "name": "numberOfValidators",
    "outputs": [{ "internalType": "uint64", "name": "", "type": "uint64" }],
    "stateMutability": "view",
    "type": "function"
  },
  {
    "inputs": [],
    "name": "owner",
    "outputs": [{ "internalType": "address", "name": "", "type": "address" }],
    "stateMutability": "view",
    "type": "function"
  },
  {
    "inputs": [
      { "internalType": "uint256", "name": "_validatorId", "type": "uint256" }
    ],
    "name": "partialWithdraw",
    "outputs": [],
    "stateMutability": "nonpayable",
    "type": "function"
  },
  {
    "inputs": [],
    "name": "pauseContract",
    "outputs": [],
    "stateMutability": "nonpayable",
    "type": "function"
  },
  {
    "inputs": [],
    "name": "paused",
    "outputs": [{ "internalType": "bool", "name": "", "type": "bool" }],
    "stateMutability": "view",
    "type": "function"
  },
  {
    "inputs": [
      { "internalType": "uint256", "name": "_validatorId", "type": "uint256" }
    ],
    "name": "phase",
    "outputs": [
      {
        "internalType": "enum IEtherFiNode.VALIDATOR_PHASE",
        "name": "validatorPhase",
        "type": "uint8"
      }
    ],
    "stateMutability": "view",
    "type": "function"
  },
  {
    "inputs": [
      {
        "internalType": "uint256[]",
        "name": "_validatorIds",
        "type": "uint256[]"
      },
      {
        "internalType": "uint32[]",
        "name": "_exitTimestamps",
        "type": "uint32[]"
      }
    ],
    "name": "processNodeExit",
    "outputs": [],
    "stateMutability": "nonpayable",
    "type": "function"
  },
  {
    "inputs": [],
    "name": "proxiableUUID",
    "outputs": [{ "internalType": "bytes32", "name": "", "type": "bytes32" }],
    "stateMutability": "view",
    "type": "function"
  },
  {
    "inputs": [
      { "internalType": "uint256", "name": "_validatorId", "type": "uint256" },
      { "internalType": "bool", "name": "_enableRestaking", "type": "bool" },
      {
        "internalType": "address",
        "name": "_withdrawalSafeAddress",
        "type": "address"
      }
    ],
    "name": "registerValidator",
    "outputs": [],
    "stateMutability": "nonpayable",
    "type": "function"
  },
  {
    "inputs": [],
    "name": "renounceOwnership",
    "outputs": [],
    "stateMutability": "nonpayable",
    "type": "function"
  },
  {
    "inputs": [{ "internalType": "bool", "name": "_enabled", "type": "bool" }],
    "name": "setEnableNodeRecycling",
    "outputs": [],
    "stateMutability": "nonpayable",
    "type": "function"
  },
  {
    "inputs": [{ "internalType": "uint8", "name": "_max", "type": "uint8" }],
    "name": "setMaxEigenLayerWithdrawals",
    "outputs": [],
    "stateMutability": "nonpayable",
    "type": "function"
  },
  {
    "inputs": [
      {
        "internalType": "uint64",
        "name": "_nonExitPenaltyDailyRate",
        "type": "uint64"
      },
      {
        "internalType": "uint64",
        "name": "_nonExitPenaltyPrincipal",
        "type": "uint64"
      }
    ],
    "name": "setNonExitPenalty",
    "outputs": [],
    "stateMutability": "nonpayable",
    "type": "function"
  },
  {
    "inputs": [
      { "internalType": "uint64", "name": "_treasury", "type": "uint64" },
      { "internalType": "uint64", "name": "_nodeOperator", "type": "uint64" },
      { "internalType": "uint64", "name": "_tnft", "type": "uint64" },
      { "internalType": "uint64", "name": "_bnft", "type": "uint64" }
    ],
    "name": "setStakingRewardsSplit",
    "outputs": [],
    "stateMutability": "nonpayable",
    "type": "function"
  },
  {
    "inputs": [
      { "internalType": "uint256", "name": "_validatorId", "type": "uint256" },
      {
        "internalType": "enum IEtherFiNode.VALIDATOR_PHASE",
        "name": "_phase",
        "type": "uint8"
      }
    ],
    "name": "setValidatorPhase",
    "outputs": [],
    "stateMutability": "nonpayable",
    "type": "function"
  },
  {
    "inputs": [],
    "name": "stakingManagerContract",
    "outputs": [{ "internalType": "address", "name": "", "type": "address" }],
    "stateMutability": "view",
    "type": "function"
  },
  {
    "inputs": [],
    "name": "stakingRewardsSplit",
    "outputs": [
      { "internalType": "uint64", "name": "treasury", "type": "uint64" },
      { "internalType": "uint64", "name": "nodeOperator", "type": "uint64" },
      { "internalType": "uint64", "name": "tnft", "type": "uint64" },
      { "internalType": "uint64", "name": "bnft", "type": "uint64" }
    ],
    "stateMutability": "view",
    "type": "function"
  },
  {
    "inputs": [],
    "name": "tnft",
    "outputs": [
      { "internalType": "contract TNFT", "name": "", "type": "address" }
    ],
    "stateMutability": "view",
    "type": "function"
  },
  {
    "inputs": [
      { "internalType": "address", "name": "newOwner", "type": "address" }
    ],
    "name": "transferOwnership",
    "outputs": [],
    "stateMutability": "nonpayable",
    "type": "function"
  },
  {
    "inputs": [],
    "name": "treasuryContract",
    "outputs": [{ "internalType": "address", "name": "", "type": "address" }],
    "stateMutability": "view",
    "type": "function"
  },
  {
    "inputs": [],
    "name": "unPauseContract",
    "outputs": [],
    "stateMutability": "nonpayable",
    "type": "function"
  },
  {
    "inputs": [
      { "internalType": "uint256", "name": "_validatorId", "type": "uint256" }
    ],
    "name": "unregisterValidator",
    "outputs": [],
    "stateMutability": "nonpayable",
    "type": "function"
  },
  {
    "inputs": [{ "internalType": "uint256", "name": "", "type": "uint256" }],
    "name": "unusedWithdrawalSafes",
    "outputs": [{ "internalType": "address", "name": "", "type": "address" }],
    "stateMutability": "view",
    "type": "function"
  },
  {
    "inputs": [
      { "internalType": "address", "name": "_address", "type": "address" },
      { "internalType": "bool", "name": "_isAdmin", "type": "bool" }
    ],
    "name": "updateAdmin",
    "outputs": [],
    "stateMutability": "nonpayable",
    "type": "function"
  },
  {
    "inputs": [
      { "internalType": "address", "name": "_address", "type": "address" },
      { "internalType": "bool", "name": "_isAdmin", "type": "bool" }
    ],
    "name": "updateEigenLayerOperatingAdmin",
    "outputs": [],
    "stateMutability": "nonpayable",
    "type": "function"
  },
  {
    "inputs": [
      { "internalType": "uint256", "name": "_validatorId", "type": "uint256" }
    ],
    "name": "updateEtherFiNode",
    "outputs": [],
    "stateMutability": "nonpayable",
    "type": "function"
  },
  {
    "inputs": [
      {
        "internalType": "address",
        "name": "newImplementation",
        "type": "address"
      }
    ],
    "name": "upgradeTo",
    "outputs": [],
    "stateMutability": "nonpayable",
    "type": "function"
  },
  {
    "inputs": [
      {
        "internalType": "address",
        "name": "newImplementation",
        "type": "address"
      },
      { "internalType": "bytes", "name": "data", "type": "bytes" }
    ],
    "name": "upgradeToAndCall",
    "outputs": [],
    "stateMutability": "payable",
    "type": "function"
  },
  { "stateMutability": "payable", "type": "receive" }
]
